README.rst
setup.cfg
setup.py
django_modelwithlog.egg-info/PKG-INFO
django_modelwithlog.egg-info/SOURCES.txt
django_modelwithlog.egg-info/dependency_links.txt
django_modelwithlog.egg-info/requires.txt
django_modelwithlog.egg-info/top_level.txt
log_models/__init__.py
log_models/apps.py
log_models/models.py
log_models/serializer_model.py
log_models/tests.py
log_models/migrations/0001_initial.py
log_models/migrations/0002_auto_20180409_1429.py
log_models/migrations/__init__.py