Metadata-Version: 1.1
Name: django-modelwithlog
Version: 1.0.1
Summary: A reusable Django Model that allows you to storeregistre actions log of models.
Home-page: https://github.com/bispogeomk/django-modelwithlog/
Author: Bispo
Author-email: bispo@geomk.com.br
License: MIT
Platform: UNKNOWN
Classifier: Development Status :: 4 - Beta
Classifier: Environment :: Web Environment
Classifier: Intended Audience :: Developers
Classifier: Operating System :: OS Independent
Classifier: Topic :: System :: Logging
Classifier: License :: OSI Approved :: MIT License
Classifier: Programming Language :: Python
Classifier: Programming Language :: Python :: 3.5
Classifier: Programming Language :: Python :: 3.6
Classifier: Framework :: Django
